LICENSE
MANIFEST.in
README.rst
example.py
setup.py
spadl.py
test.py
spadl.egg-info/PKG-INFO
spadl.egg-info/SOURCES.txt
spadl.egg-info/dependency_links.txt
spadl.egg-info/not-zip-safe
spadl.egg-info/top_level.txt