Metadata-Version: 1.0
Name: spadl
Version: 0.3
Summary: This package provides a standard logging handler which writes log records to DbgLog.
Home-page: https://github.com/mila/spadl
Author: Miloslav Pojman
Author-email: miloslav.pojman@gmail.com
License: UNKNOWN
Platform: UNKNOWN
Classifier: Intended Audience :: Developers
Classifier: License :: OSI Approved :: BSD License
Classifier: Operating System :: OS Independent
Classifier: Programming Language :: Python
Classifier: Topic :: System :: Logging
